bestchange_api/__init__.py
bestchange_api/main.py
bestchange_api-3.1.0.0.dist-info/LICENSE
bestchange_api-3.1.0.0.dist-info/LICENSE.txt
bestchange_api-3.1.0.0.dist-info/METADATA
bestchange_api-3.1.0.0.dist-info/WHEEL
bestchange_api-3.1.0.0.dist-info/top_level.txt
bestchange_api-3.1.0.0.dist-info/RECORD
