Metadata-Version: 2.1
Name: bestchange_api
Version: 3.1.0.0
Summary: Библиотека для работы с "api" сервиса bestchange.ru
Home-page: https://maksam07.com
Author: maksam07
Author-email: maksam07@gmail.com
Project-URL: Source, https://github.com/maksam07/bestchange_api
Classifier: License :: OSI Approved :: BSD License
Classifier: Programming Language :: Python
Classifier: Programming Language :: Python :: 3
Classifier: Programming Language :: Python :: 3 :: Only
Classifier: Programming Language :: Python :: 3.8
Classifier: Programming Language :: Python :: 3.9
Classifier: Programming Language :: Python :: 3.10
Requires-Python: >=3.8
License-File: LICENSE
License-File: LICENSE.txt
